{"stats":{"minecraft:killed_by":{"minecraft:husk":1,"mialliance:mi":4,"irons_spellbooks:cryomancer":1,"minecraft:witch":1,"minecraft:zombie":1},"minecraft:crafted":{"minecraft:oak_planks":372,"magistuarmory:diamond_zweihander":1,"siegemachines:siege_workbench":1,"magistuarmory:hilt":2,"minecraft:iron_axe":2,"magistuarmory:diamond_shortsword":1,"irons_spellbooks:copper_spell_book":1,"minecraft:crafting_table":1,"minecraft:air":0,"siegemachines:turret_base":5,"siegemachines:ballista":1,"siegemachines:beam":20,"quark:oak_chest":8,"minecraft:iron_ingot":10,"minecraft:compass":1,"minecraft:torch":12,"magistuarmory:leather_strip":6},"minecraft:picked_up":{"irons_spellbooks:scroll":2,"minecraft:azure_bluet":12,"minecraft:chainmail_boots":1,"simplehats:hatbag_rare":5,"mialliance:mi_essence":8,"immersiveengineering:craftingtable":1,"minecraft:enchanted_book":29,"minecraft:string":50,"minecraft:raw_copper":13,"minecraft:iron_axe":1,"minecraft:cracked_stone_bricks":2,"irons_spellbooks:arcane_essence":7,"minecraft:smooth_stone":7,"minecraft:cobbled_deepslate":8,"minecraft:beef":10,"immersiveengineering:crate":3,"minecraft:player_head":7,"irons_spellbooks:epic_ink":1,"minecraft:iron_nugget":2,"irons_spellbooks:inscription_table":1,"minecraft:crimson_sign":2,"simplehats:madscientist":1,"minecraft:stick":17,"minecraft:raw_iron":10,"immersiveengineering:shader_bag_epic":8,"simplehats:hatbag_common":14,"minecraft:copper_ingot":6,"minecraft:green_bed":2,"minecraft:torch":7,"doggytalents:whistle":1,"simplehats:sonichood":1,"sophisticatedbackpacks:backpack":2,"simplehats:worms_mine":1,"minecraft:porkchop":3,"simplehats:ushanka":1,"minecraft:carrot":18,"minecraft:redstone":2,"mialliance:metallium":1,"simplehats:camerabeard":1,"minecraft:arrow":19,"minecraft:rotten_flesh":78,"simplehats:crown":1,"minecraft:nether_bricks":2,"minecraft:hay_block":54,"supplementaries:antique_ink":2,"minecraft:mutton":1,"minecraft:bone_block":9,"minecraft:white_wool":2,"minecraft:cobblestone":1,"mialliance:mistrum":3,"minecraft:leather_chestplate":1,"minecraft:glow_ink_sac":1,"minecraft:potato":1,"mialliance:mitrean_tiles":1,"minecraft:leather":9,"magistuarmory:diamond_zweihander":2,"minecraft:flint":1,"minecraft:tuff":9,"simplehats:beret_ribbon":1,"minecraft:oak_log":223,"minecraft:chainmail_chestplate":1,"minecraft:golden_boots":2,"minecraft:cobblestone_wall":1,"minecraft:gunpowder":3,"minecraft:cobblestone_stairs":2,"minecraft:dirt":1,"simplehats:hatbag_epic":4,"irons_spellbooks:rare_ink":1,"minecraft:purple_carpet":2,"irons_spellbooks:common_ink":2,"minecraft:red_carpet":5,"minecraft:bone":20,"minecraft:apple":1,"minecraft:stone_bricks":13,"minecraft:bow":3,"minecraft:wheat_seeds":2,"minecraft:iron_ingot":74,"minecraft:cobweb":9,"minecraft:mossy_stone_bricks":2,"simplehats:hatbag_uncommon":8,"minecraft:glass_bottle":1,"minecraft:oak_planks":2,"simplehats:babyturtle":1,"simplehats:baseballhatjuly":1,"simplehats:rock":1,"mialliance:familiar_bloom":1,"minecraft:red_concrete_powder":1,"minecraft:chiseled_stone_bricks":1,"simplehats:sheep":2,"minecraft:stone_brick_slab":1,"minecraft:gravel":4,"minecraft:sand":10,"immersiveengineering:circuit_table":1,"minecraft:spider_eye":13,"minecraft:mossy_stone_brick_slab":1,"simplehats:jesterhat":1,"irons_spellbooks:ice_rune":2,"siegemachines:ballista":1,"mialliance:mistrum_brick":1,"tetra:geode":1,"immersiveengineering:seed":1,"minecraft:diamond":2,"mialliance:miseed":2,"minecraft:chainmail_helmet":2,"minecraft:bread":1,"simplehats:dangeresquejuly":2,"minecraft:oak_sapling":29,"minecraft:coal":30,"simplehats:hatbag_summer":3,"minecraft:ender_pearl":1},"minecraft:custom":{"minecraft:interact_with_anvil":2,"minecraft:mob_kills":221,"minecraft:interact_with_crafting_table":15,"minecraft:open_barrel":10,"minecraft:eat_cake_slice":2,"minecraft:leave_game":5,"minecraft:time_since_death":13306,"minecraft:climb_one_cm":11302,"champions:champion_mobs_killed":202,"minecraft:sprint_one_cm":266749,"minecraft:walk_one_cm":656358,"minecraft:drop":28,"minecraft:damage_dealt_absorbed":936,"minecraft:play_time":197844,"minecraft:deaths":8,"minecraft:sneak_time":467,"minecraft:walk_under_water_one_cm":11745,"minecraft:jump":2447,"minecraft:interact_with_brewingstand":1,"minecraft:walk_on_water_one_cm":31674,"minecraft:total_world_time":197844,"minecraft:interact_with_furnace":5,"minecraft:interact_with_loom":1,"minecraft:sleep_in_bed":7,"minecraft:time_since_rest":13352,"minecraft:damage_taken":7540,"minecraft:damage_absorbed":120,"minecraft:trigger_trapped_chest":2,"minecraft:damage_dealt":29011,"minecraft:swim_one_cm":9673,"minecraft:fly_one_cm":489914,"minecraft:open_chest":135,"minecraft:crouch_one_cm":898,"minecraft:interact_with_smoker":1,"minecraft:fall_one_cm":64797},"minecraft:killed":{"goblinsanddungeons:goblo":2,"minecraft:witch":2,"minecraft:spider":43,"irons_spellbooks:cryomancer":2,"minecraft:skeleton":23,"minecraft:chicken":1,"minecraft:silverfish":17,"minecraft:husk":5,"goblinsanddungeons:gob":3,"ba_bt:bt_cultist":1,"minecraft:creeper":2,"mialliance:mi":19,"minecraft:zombie":83,"friendsandfoes:moobloom":1,"minecraft:cow":4},"minecraft:dropped":{"minecraft:enchanted_book":2,"minecraft:golden_boots":1,"minecraft:wheat_seeds":1,"minecraft:oak_log":20,"mialliance:metallium":1,"simplehats:sheep":1,"minecraft:chainmail_helmet":2,"minecraft:leather_helmet":1,"minecraft:stick":1,"magistuarmory:diamond_zweihander":2,"minecraft:player_head":2,"minecraft:iron_nugget":1,"mialliance:familiar_bloom":1,"minecraft:cobbled_deepslate":1,"minecraft:tuff":9,"minecraft:rotten_flesh":5,"immersiveengineering:shader":1,"minecraft:chainmail_chestplate":1,"minecraft:leather_chestplate":1,"minecraft:chainmail_boots":1,"minecraft:leather_leggings":1,"minecraft:arrow":3,"minecraft:bow":1},"minecraft:used":{"irons_spellbooks:inscription_table":1,"mialliance:mitrean_tiles":1,"minecraft:mossy_stone_brick_slab":1,"minecraft:player_head":4,"minecraft:torch":20,"immersiveengineering:craftingtable":1,"minecraft:nether_bricks":1,"tconstruct:hand_axe":62,"immersiveengineering:circuit_table":1,"minecraft:iron_axe":316,"carryon:entity_item":1,"minecraft:iron_boots":1,"minecraft:stone_bricks":2,"carryon:tile_item":1,"minecraft:oak_sapling":22,"immersiveengineering:crate":3,"minecraft:cooked_beef":11,"minecraft:mossy_stone_bricks":2,"minecraft:cobblestone_stairs":2,"cgm:pistol":37,"minecraft:oak_planks":28,"minecraft:green_bed":2,"minecraft:sand":6,"magistuarmory:diamond_zweihander":175,"siegemachines:ballista":2,"mialliance:mistrum_brick":1,"minecraft:bread":25,"minecraft:iron_pickaxe":68,"siegemachines:siege_workbench":1,"minecraft:chiseled_stone_bricks":1,"minecraft:enchanted_book":1,"minecraft:cobblestone":1,"minecraft:red_concrete_powder":1,"quark:oak_chest":8,"minecraft:smooth_stone":2},"minecraft:mined":{"mialliance:mi_beacon":9,"minecraft:tuff":10,"mialliance:mitrean_tiles":1,"minecraft:deepslate_diamond_ore":2,"minecraft:mossy_stone_brick_slab":1,"minecraft:cobblestone_stairs":2,"farmersdelight:wild_carrots":18,"minecraft:nether_bricks":2,"minecraft:chiseled_stone_bricks":1,"goblinsanddungeons:urn":1,"minecraft:smooth_stone":5,"minecraft:hay_block":54,"minecraft:red_concrete_powder":1,"minecraft:azure_bluet":12,"minecraft:cobblestone_slab":1,"minecraft:iron_bars":1,"irons_spellbooks:inscription_table":1,"minecraft:white_wool":1,"immersiveengineering:craftingtable":1,"minecraft:green_bed":2,"supplementaries:book_pile":1,"mialliance:mistrum_soil":1,"minecraft:stone_brick_slab":2,"minecraft:torch":5,"minecraft:tall_grass":1,"minecraft:cobblestone":3,"minecraft:oak_planks":2,"mialliance:familiar_bloom":1,"minecraft:wall_torch":2,"minecraft:cobblestone_wall":1,"mialliance:mi_beacon_inactive":4,"immersiveengineering:circuit_table":1,"minecraft:grass":24,"minecraft:oak_log":209,"minecraft:gravel":5,"minecraft:sand":10,"minecraft:dirt":1,"mialliance:metalliumore_deepslate":1,"minecraft:cracked_stone_bricks":2,"minecraft:stone_bricks":13,"minecraft:mossy_stone_bricks":2,"minecraft:oak_leaves":47,"immersiveengineering:crate":3,"minecraft:deepslate":1},"minecraft:broken":{"minecraft:iron_boots":1,"minecraft:iron_leggings":1,"minecraft:iron_axe":1,"minecraft:iron_helmet":1}},"DataVersion":2975}